project215_data_transformations/__init__.py
project215_data_transformations/cross_correlation2d.py
project215_data_transformations/transpose2d.py
project215_data_transformations/window1d.py
project215_data_transformations-0.4.0.dist-info/METADATA
project215_data_transformations-0.4.0.dist-info/WHEEL
project215_data_transformations-0.4.0.dist-info/RECORD
