Metadata-Version: 2.1
Name: project215-data-transformations
Version: 0.4.0
Summary: This package includes transpose, time series windowing and cross-correlation libraries.
Author: marius uogle
Author-email: uogelemarius@gmail.com
Requires-Python: >=3.9,<4.0
Classifier: Programming Language :: Python :: 3
Classifier: Programming Language :: Python :: 3.9
Classifier: Programming Language :: Python :: 3.10
Classifier: Programming Language :: Python :: 3.11
Requires-Dist: numpy (==1.26.1)
